LICENSE
MANIFEST.in
README.rst
setup.py
bashkirtagger/__init__.py
bashkirtagger/index2tag.json
bashkirtagger/index2word.json
bashkirtagger/tagger.py
bashkirtagger/test_tagger.py
bashkirtagger.egg-info/PKG-INFO
bashkirtagger.egg-info/SOURCES.txt
bashkirtagger.egg-info/dependency_links.txt
bashkirtagger.egg-info/not-zip-safe
bashkirtagger.egg-info/requires.txt
bashkirtagger.egg-info/top_level.txt