Metadata-Version: 1.1
Name: bashkirtagger
Version: 0.6.2
Summary: Utility for part-of-speech tagging of Bashkir text
Home-page: https://github.com/nevmenandr/bashkirtagger
Author: Boris Orekhov
Author-email: nevmenandr@gmail.com
License: GPL
Keywords: nlp bashkir pos tagger
Platform: UNKNOWN
Classifier: Development Status :: 4 - Beta
Classifier: Natural Language :: Russian
Classifier: Programming Language :: Python :: 3.5
Classifier: Programming Language :: Python :: 3.6
Classifier: Topic :: Text Processing :: Linguistic
Classifier: Intended Audience :: Developers
